setup.py
python_social.egg-info/PKG-INFO
python_social.egg-info/SOURCES.txt
python_social.egg-info/dependency_links.txt
python_social.egg-info/top_level.txt
social/__init__.py
social/metadata.py
social/facebook/__init__.py
social/facebook/backends.py
social/facebook/django_decorators.py
social/facebook/facebook.py
social/facebook/flask_decorators.py
social/facebook/metadata.py
social/facebook/settings.py
social/facebook/signals.py
social/facebook/urls.py
social/facebook/views.py