Metadata-Version: 1.0
Name: python-social
Version: 0.1
Summary: Integrate with any third party, easily.
Home-page: https://github.com/aurorasoftware/python-social
Author: Dan Loewenherz
Author-email: dan@dlo.me
License: UNKNOWN
Platform: UNKNOWN
